vtb_django_commands/__about__.py
vtb_django_commands/__init__.py
vtb_django_commands/management/__init__.py
vtb_django_commands/management/commands/__init__.py
vtb_django_commands/management/commands/createsuperuser_from_env.py
vtb_django_commands/management/commands/export_authorizer_schema.py
vtb_django_commands/management/commands/get_admin_token.py
vtb_django_commands/management/commands/import_authorizer_schema.py
vtb_django_commands-1.0.4.dist-info/METADATA
vtb_django_commands-1.0.4.dist-info/WHEEL
vtb_django_commands-1.0.4.dist-info/top_level.txt
vtb_django_commands-1.0.4.dist-info/RECORD
